[{"label":"Affenpinscher","value":"Affenpinscher"},{"label":"Afghan Hound","value":"Afghan Hound"},{"label":"African Hunting Dog","value":"African Hunting Dog"},{"label":"Airedale Terrier","value":"Airedale Terrier"},{"label":"Akbash Dog","value":"Akbash Dog"},{"label":"Akita","value":"Akita"},{"label":"Alapaha Blue Blood Bulldog","value":"Alapaha Blue Blood Bulldog"},{"label":"Alaskan Husky","value":"Alaskan Husky"},{"label":"Alaskan Malamute","value":"Alaskan Malamute"},{"label":"American Bulldog","value":"American Bulldog"},{"label":"American Bully","value":"American Bully"},{"label":"American Eskimo Dog","value":"American Eskimo Dog"},{"label":"American Eskimo Dog (Miniature)","value":"American Eskimo Dog (Miniature)"},{"label":"American Foxhound","value":"American Foxhound"},{"label":"American Pit Bull Terrier","value":"American Pit Bull Terrier"},{"label":"American Staffordshire Terrier","value":"American Staffordshire Terrier"},{"label":"American Water Spaniel","value":"American Water Spaniel"},{"label":"Anatolian Shepherd Dog","value":"Anatolian Shepherd Dog"},{"label":"Appenzeller Sennenhund","value":"Appenzeller Sennenhund"},{"label":"Australian Cattle Dog","value":"Australian Cattle Dog"},{"label":"Australian Kelpie","value":"Australian Kelpie"},{"label":"Australian Shepherd","value":"Australian Shepherd"},{"label":"Australian Terrier","value":"Australian Terrier"},{"label":"Azawakh","value":"Azawakh"},{"label":"Barbet","value":"Barbet"},{"label":"Basenji","value":"Basenji"},{"label":"Basset Bleu de Gascogne","value":"Basset Bleu de Gascogne"},{"label":"Basset Hound","value":"Basset Hound"},{"label":"Beagle","value":"Beagle"},{"label":"Bearded Collie","value":"Bearded Collie"},{"label":"Beauceron","value":"Beauceron"},{"label":"Bedlington Terrier","value":"Bedlington Terrier"},{"label":"Belgian Malinois","value":"Belgian Malinois"},{"label":"Belgian Tervuren","value":"Belgian Tervuren"},{"label":"Bernese Mountain Dog","value":"Bernese Mountain Dog"},{"label":"Bichon Frise","value":"Bichon Frise"},{"label":"Black and Tan Coonhound","value":"Black and Tan Coonhound"},{"label":"Bloodhound","value":"Bloodhound"},{"label":"Bluetick Coonhound","value":"Bluetick Coonhound"},{"label":"Boerboel","value":"Boerboel"},{"label":"Border Collie","value":"Border Collie"},{"label":"Border Terrier","value":"Border Terrier"},{"label":"Boston Terrier","value":"Boston Terrier"},{"label":"Bouvier des Flandres","value":"Bouvier des Flandres"},{"label":"Boxer","value":"Boxer"},{"label":"Boykin Spaniel","value":"Boykin Spaniel"},{"label":"Bracco Italiano","value":"Bracco Italiano"},{"label":"Briard","value":"Briard"},{"label":"Brittany","value":"Brittany"},{"label":"Bull Terrier","value":"Bull Terrier"},{"label":"Bull Terrier (Miniature)","value":"Bull Terrier (Miniature)"},{"label":"Bullmastiff","value":"Bullmastiff"},{"label":"Cairn Terrier","value":"Cairn Terrier"},{"label":"Cane Corso","value":"Cane Corso"},{"label":"Cardigan Welsh Corgi","value":"Cardigan Welsh Corgi"},{"label":"Catahoula Leopard Dog","value":"Catahoula Leopard Dog"},{"label":"Caucasian Shepherd (Ovcharka)","value":"Caucasian Shepherd (Ovcharka)"},{"label":"Cavalier King Charles Spaniel","value":"Cavalier King Charles Spaniel"},{"label":"Chesapeake Bay Retriever","value":"Chesapeake Bay Retriever"},{"label":"Chinese Crested","value":"Chinese Crested"},{"label":"Chinese Shar-Pei","value":"Chinese Shar-Pei"},{"label":"Chinook","value":"Chinook"},{"label":"Chow Chow","value":"Chow Chow"},{"label":"Clumber Spaniel","value":"Clumber Spaniel"},{"label":"Cocker Spaniel","value":"Cocker Spaniel"},{"label":"Cocker Spaniel (American)","value":"Cocker Spaniel (American)"},{"label":"Coton de Tulear","value":"Coton de Tulear"},{"label":"Dalmatian","value":"Dalmatian"},{"label":"Doberman Pinscher","value":"Doberman Pinscher"},{"label":"Dogo Argentino","value":"Dogo Argentino"},{"label":"Dutch Shepherd","value":"Dutch Shepherd"},{"label":"English Setter","value":"English Setter"},{"label":"English Shepherd","value":"English Shepherd"},{"label":"English Springer Spaniel","value":"English Springer Spaniel"},{"label":"English Toy Spaniel","value":"English Toy Spaniel"},{"label":"English Toy Terrier","value":"English Toy Terrier"},{"label":"Eurasier","value":"Eurasier"},{"label":"Field Spaniel","value":"Field Spaniel"},{"label":"Finnish Lapphund","value":"Finnish Lapphund"},{"label":"Finnish Spitz","value":"Finnish Spitz"},{"label":"French Bulldog","value":"French Bulldog"},{"label":"German Pinscher","value":"German Pinscher"},{"label":"German Shepherd Dog","value":"German Shepherd Dog"},{"label":"German Shorthaired Pointer","value":"German Shorthaired Pointer"},{"label":"Giant Schnauzer","value":"Giant Schnauzer"},{"label":"Glen of Imaal Terrier","value":"Glen of Imaal Terrier"},{"label":"Golden Retriever","value":"Golden Retriever"},{"label":"Gordon Setter","value":"Gordon Setter"},{"label":"Great Dane","value":"Great Dane"},{"label":"Great Pyrenees","value":"Great Pyrenees"},{"label":"Greyhound","value":"Greyhound"},{"label":"Griffon Bruxellois","value":"Griffon Bruxellois"},{"label":"Harrier","value":"Harrier"},{"label":"Havanese","value":"Havanese"},{"label":"Irish Setter","value":"Irish Setter"},{"label":"Irish Terrier","value":"Irish Terrier"},{"label":"Irish Wolfhound","value":"Irish Wolfhound"},{"label":"Italian Greyhound","value":"Italian Greyhound"},{"label":"Japanese Chin","value":"Japanese Chin"},{"label":"Japanese Spitz","value":"Japanese Spitz"},{"label":"Keeshond","value":"Keeshond"},{"label":"Komondor","value":"Komondor"},{"label":"Kooikerhondje","value":"Kooikerhondje"},{"label":"Kuvasz","value":"Kuvasz"},{"label":"Labrador Retriever","value":"Labrador Retriever"},{"label":"Lagotto Romagnolo","value":"Lagotto Romagnolo"},{"label":"Lancashire Heeler","value":"Lancashire Heeler"},{"label":"Leonberger","value":"Leonberger"},{"label":"Lhasa Apso","value":"Lhasa Apso"},{"label":"Maltese","value":"Maltese"},{"label":"Miniature American Shepherd","value":"Miniature American Shepherd"},{"label":"Miniature Pinscher","value":"Miniature Pinscher"},{"label":"Miniature Schnauzer","value":"Miniature Schnauzer"},{"label":"Newfoundland","value":"Newfoundland"},{"label":"Norfolk Terrier","value":"Norfolk Terrier"},{"label":"Norwich Terrier","value":"Norwich Terrier"},{"label":"Nova Scotia Duck Tolling Retriever","value":"Nova Scotia Duck Tolling Retriever"},{"label":"Old English Sheepdog","value":"Old English Sheepdog"},{"label":"Olde English Bulldogge","value":"Olde English Bulldogge"},{"label":"Papillon","value":"Papillon"},{"label":"Pekingese","value":"Pekingese"},{"label":"Pembroke Welsh Corgi","value":"Pembroke Welsh Corgi"},{"label":"Perro de Presa Canario","value":"Perro de Presa Canario"},{"label":"Pharaoh Hound","value":"Pharaoh Hound"},{"label":"Plott","value":"Plott"},{"label":"Pomeranian","value":"Pomeranian"},{"label":"Poodle (Miniature)","value":"Poodle (Miniature)"},{"label":"Poodle (Toy)","value":"Poodle (Toy)"},{"label":"Pug","value":"Pug"},{"label":"Puli","value":"Puli"},{"label":"Pumi","value":"Pumi"},{"label":"Rat Terrier","value":"Rat Terrier"},{"label":"Redbone Coonhound","value":"Redbone Coonhound"},{"label":"Rhodesian Ridgeback","value":"Rhodesian Ridgeback"},{"label":"Rottweiler","value":"Rottweiler"},{"label":"Russian Toy","value":"Russian Toy"},{"label":"Saint Bernard","value":"Saint Bernard"},{"label":"Saluki","value":"Saluki"},{"label":"Samoyed","value":"Samoyed"},{"label":"Schipperke","value":"Schipperke"},{"label":"Scottish Deerhound","value":"Scottish Deerhound"},{"label":"Scottish Terrier","value":"Scottish Terrier"},{"label":"Shetland Sheepdog","value":"Shetland Sheepdog"},{"label":"Shiba Inu","value":"Shiba Inu"},{"label":"Shih Tzu","value":"Shih Tzu"},{"label":"Shiloh Shepherd","value":"Shiloh Shepherd"},{"label":"Siberian Husky","value":"Siberian Husky"},{"label":"Silky Terrier","value":"Silky Terrier"},{"label":"Smooth Fox Terrier","value":"Smooth Fox Terrier"},{"label":"Soft Coated Wheaten Terrier","value":"Soft Coated Wheaten Terrier"},{"label":"Spanish Water Dog","value":"Spanish Water Dog"},{"label":"Spinone Italiano","value":"Spinone Italiano"},{"label":"Staffordshire Bull Terrier","value":"Staffordshire Bull Terrier"},{"label":"Standard Schnauzer","value":"Standard Schnauzer"},{"label":"Swedish Vallhund","value":"Swedish Vallhund"},{"label":"Thai Ridgeback","value":"Thai Ridgeback"},{"label":"Tibetan Mastiff","value":"Tibetan Mastiff"},{"label":"Tibetan Spaniel","value":"Tibetan Spaniel"},{"label":"Tibetan Terrier","value":"Tibetan Terrier"},{"label":"Toy Fox Terrier","value":"Toy Fox Terrier"},{"label":"Treeing Walker Coonhound","value":"Treeing Walker Coonhound"},{"label":"Vizsla","value":"Vizsla"},{"label":"Weimaraner","value":"Weimaraner"},{"label":"Welsh Springer Spaniel","value":"Welsh Springer Spaniel"},{"label":"West Highland White Terrier","value":"West Highland White Terrier"},{"label":"Whippet","value":"Whippet"},{"label":"White Shepherd","value":"White Shepherd"},{"label":"Wire Fox Terrier","value":"Wire Fox Terrier"},{"label":"Wirehaired Pointing Griffon","value":"Wirehaired Pointing Griffon"},{"label":"Wirehaired Vizsla","value":"Wirehaired Vizsla"},{"label":"Xoloitzcuintli","value":"Xoloitzcuintli"},{"label":"Yorkshire Terrier","value":"Yorkshire Terrier"}]